mave2imap/CombineMultiExp.py
mave2imap/ReadAssembler.py
mave2imap/ReadParser.py
mave2imap/__init__.py
mave2imap/_version.py
mave2imap/lr_tools.py
mave2imap/mave2imap.py
mave2imap/py.typed
mave2imap/tools/aa2nuc.pickle
mave2imap/tools/nuc2aa.pickle
mave2imap/tools/nuc2abundance.pickle
mave2imap-1.0.0.0.5.dist-info/licenses/LICENSE
mave2imap-1.0.0.0.5.dist-info/METADATA
mave2imap-1.0.0.0.5.dist-info/WHEEL
mave2imap-1.0.0.0.5.dist-info/entry_points.txt
mave2imap-1.0.0.0.5.dist-info/top_level.txt
mave2imap-1.0.0.0.5.dist-info/RECORD
