Metadata-Version: 2.4
Name: mave2imap
Version: 1.0.0.0.5
Summary: This project is intended for infering and mapping interface hotspots based on results from MAVE (Multiplexed Assays of Variant Effects).
Author-email: Aravindan Arun Nadaradjane <arunnatrajanravi@gmail.com>, Juan Pablo Guzmán Álvarez <jpguz0709@hotmail.com>, "Oscar H.P. Ramos" <oscar.pereira-ramos@cea.fr>, Raphael Guerois <raphael.guerois@cea.fr>
License-Expression: MIT
Classifier: Programming Language :: Python :: 3
Requires-Python: >=3.8
License-File: LICENSE
Requires-Dist: async-lru==2.0.4
Requires-Dist: h11==0.14.0
Requires-Dist: httpcore==1.0.7
Requires-Dist: httpx==0.28.1
Requires-Dist: jupyter-lsp==2.2.5
Requires-Dist: jupyterlab==4.3.4
Requires-Dist: kaleido==0.2.1
Requires-Dist: nglview==3.1.2
Requires-Dist: notebook==7.3.2
Requires-Dist: h5py==3.11.0
Dynamic: license-file
